<?xml version="1.0" encoding="UTF-8"?>

<databaseChangeLog xmlns="http://www.liquibase.org/xml/ns/dbchangelog"
	xmlns:xsi="http://www.w3.org/2001/XMLSchema-instance"
	xsi:schemaLocation="http://www.liquibase.org/xml/ns/dbchangelog
         http://www.liquibase.org/xml/ns/dbchangelog/dbchangelog-3.1.xsd">
	<changeSet id="3" author="gaurav">

		<createTable tableName="cards">
			<column name="id" type="bigint" autoIncrement="true">
				<constraints primaryKey="true" nullable="false" />
			</column>
			<column name="created_by" type="bigint">
				<constraints nullable="false" />
			</column>
			<column name="category_id" type="bigint">
				<constraints nullable="false" />
			</column>
			<column name="title" type="varchar(255)">
				<constraints nullable="false" />
			</column>
			<column name="content" type="varchar(2048)">
				<constraints nullable="false" />
			</column>
			<column name="photo_uri" type="TEXT">
				<constraints nullable="false" />
			</column>
			<column name="is_published" type="boolean">
				<constraints nullable="false" />
			</column>
			<column name="created_at" type="datetime">
				<constraints nullable="false" />
			</column>
			<column name="updated_at" type="datetime">
				<constraints nullable="false" />
			</column>
		</createTable>


		<addAutoIncrement columnDataType="bigint" columnName="id"
			incrementBy="1" startWith="1000" tableName="users" />

		<addForeignKeyConstraint baseColumnNames="created_by"
			baseTableName="cards" constraintName="fk_users_already_exist"
			onDelete="CASCADE" onUpdate="RESTRICT" referencedColumnNames="id"
			referencedTableName="users" />
		<addForeignKeyConstraint baseColumnNames="category_id"
			baseTableName="cards" constraintName="fk_category_must_exist"
			onDelete="CASCADE" onUpdate="RESTRICT" referencedColumnNames="id"
			referencedTableName="categories" />

	</changeSet>
</databaseChangeLog>